s3a_decorrelation_toolbox/__init__.py
s3a_decorrelation_toolbox/decorr_toolbox.py
s3a_decorrelation_toolbox/demo_s3a_decorrelator.py
s3a_decorrelation_toolbox/percussive_harmonic_decorrelator.py
s3a_decorrelation_toolbox/s3a_decorrelator.py
s3a_decorrelation_toolbox-0.2.9.dist-info/LICENSE
s3a_decorrelation_toolbox-0.2.9.dist-info/METADATA
s3a_decorrelation_toolbox-0.2.9.dist-info/WHEEL
s3a_decorrelation_toolbox-0.2.9.dist-info/top_level.txt
s3a_decorrelation_toolbox-0.2.9.dist-info/RECORD
