Metadata-Version: 2.1
Name: s3a-decorrelation-toolbox
Version: 0.2.9
Summary: Decorrelation algorithm and toolbox for diffuse sound objects and general upmix
Home-page: https://github.com/s3a-spatialaudio/decorrelation-python-toolbox
Author: Michael Cousins
Author-email: michaelcousins56@gmail.com
License: ISC
Platform: UNKNOWN
Classifier: Programming Language :: Python :: 3
Classifier: Development Status :: 3 - Alpha
Classifier: License :: OSI Approved :: ISC License (ISCL)
Classifier: Operating System :: OS Independent
Classifier: Topic :: Multimedia :: Sound/Audio
Requires-Dist: numpy (>=1.16.2)
Requires-Dist: scipy (>=1.2.1)
Requires-Dist: soundfile (>=0.10.0)
Requires-Dist: librosa (>=0.6.3)
Requires-Dist: acoustics (>=0.1.2)
Requires-Dist: pyloudnorm (>=0.0.1)
Requires-Dist: matplotlib (>=3.0.2)
